mysqlite.py
mysqlite-0.1.4.dist-info/WHEEL
mysqlite-0.1.4.dist-info/METADATA
mysqlite-0.1.4.dist-info/RECORD
