Metadata-Version: 2.1
Name: mysqlite
Version: 0.1.4
Summary: mysqlite.Database('database_name.db')
Author: Django-B
Author-email: django.ppp@gmail.com
Requires-Python: >=3.8,<4.0
Classifier: Programming Language :: Python :: 3
Classifier: Programming Language :: Python :: 3.8
Classifier: Programming Language :: Python :: 3.9
Classifier: Programming Language :: Python :: 3.10
Classifier: Programming Language :: Python :: 3.11
